monosolver/__init__.py
monosolver-0.0.1.dist-info/DESCRIPTION.rst
monosolver-0.0.1.dist-info/METADATA
monosolver-0.0.1.dist-info/RECORD
monosolver-0.0.1.dist-info/WHEEL
monosolver-0.0.1.dist-info/metadata.json
monosolver-0.0.1.dist-info/top_level.txt
